bcclassreport/__init__.py
bcclassreport/core.py
bcclassreport-1.0.0.dist-info/licenses/LICENSE
bcclassreport-1.0.0.dist-info/METADATA
bcclassreport-1.0.0.dist-info/WHEEL
bcclassreport-1.0.0.dist-info/top_level.txt
bcclassreport-1.0.0.dist-info/RECORD
